README.rst
setup.cfg
setup.py
CyDeTs.egg-info/PKG-INFO
CyDeTs.egg-info/SOURCES.txt
CyDeTs.egg-info/dependency_links.txt
CyDeTs.egg-info/requires.txt
CyDeTs.egg-info/top_level.txt
cydets/__init__.py
cydets/algorithm.py