Metadata-Version: 1.2
Name: CyDeTs
Version: 1.0
Summary: Cycle Detection in Time Series (CyDeTS). An algorithm to detect cycles in times series along with their respective amplitude and duration.
Home-page: https://github.com/oemof/cydets
Author: Cord Kaldemeyer, Francesco Witte
Author-email: francesco.witte@hs-flensburg.de
License: GPL-3.0
Platform: UNKNOWN
Requires-Python: >=3
